dock_craftsman/__init__.py
dock_craftsman/docker_image_builder.py
dock_craftsman/docker_image_builder_socketio.py
dock_craftsman/docker_manager.py
dock_craftsman/dockerfile_generator.py
dock_craftsman/utils.py
dock_craftsman/docker/__init__.py
dock_craftsman/docker/container.py
dock_craftsman/docker/image.py
dock_craftsman/docker/network.py
dock_craftsman/docker/volume.py
dock_craftsman/supervisor/__init__.py
dock_craftsman/supervisor/visord.py
dock_craftsman-0.0.17.dist-info/LICENSE
dock_craftsman-0.0.17.dist-info/METADATA
dock_craftsman-0.0.17.dist-info/WHEEL
dock_craftsman-0.0.17.dist-info/top_level.txt
dock_craftsman-0.0.17.dist-info/RECORD
